biocore/__init__.py
biocore/base.py
biocore/data_handling.py
biocore/arrow/__init__.py
biocore/arrow/arrow.py
biocore/csr/__init__.py
biocore/csr/csr.py
biocore/dask/__init__.py
biocore/dask/dask.py
biocore/dataset/__init__.py
biocore/dataset/dataset.py
biocore/dict/__init__.py
biocore/dict/dict.py
biocore/dicts/__init__.py
biocore/dicts/dicts.py
biocore/io/__init__.py
biocore/io/io.py
biocore/iterabledataset/__init__.py
biocore/iterabledataset/iterabledataset.py
biocore/list/__init__.py
biocore/list/list.py
biocore/numpy/__init__.py
biocore/numpy/numpy.py
biocore/pandas/__init__.py
biocore/pandas/pandas.py
biocore/polars/__init__.py
biocore/polars/polars.py
biocore/ray/__init__.py
biocore/ray/ray.py
biocore/row_dict/__init__.py
biocore/row_dict/row_dict.py
biocore/utils/__init__.py
biocore/utils/import_util.py
biocore/utils/inspect.py
biocore/utils/logging.py
biocore/utils/naming.py
biocore/utils/py_util.py
biocore/utils/version.py
biocore-1.1.1.dist-info/LICENSE
biocore-1.1.1.dist-info/METADATA
biocore-1.1.1.dist-info/WHEEL
biocore-1.1.1.dist-info/top_level.txt
biocore-1.1.1.dist-info/RECORD
